jianzipu/__init__.py
jianzipu/constant.py
jianzipu/data.yaml
jianzipu/grammar.py
jianzipu/ids.py
jianzipu/note.py
jianzipu/parser.py
jianzipu-0.4.1.dist-info/METADATA
jianzipu-0.4.1.dist-info/WHEEL
jianzipu-0.4.1.dist-info/RECORD
