Metadata-Version: 2.1
Name: jianzipu
Version: 0.4.1
Summary: 根据古琴减字谱读法渲染减字图像
Author: alephpi
Author-email: maosicheng98@gmail.com
Requires-Python: >=3.11,<4.0
Classifier: Development Status :: 3 - Alpha
Classifier: License :: OSI Approved :: GNU Affero General Public License v3 or later (AGPLv3+)
Classifier: Natural Language :: Chinese (Simplified)
Classifier: Natural Language :: Chinese (Traditional)
Classifier: Programming Language :: Python :: 3
Classifier: Programming Language :: Python :: 3.11
Classifier: Topic :: Software Development :: Libraries
Classifier: Topic :: Text Processing :: Fonts
Requires-Dist: pyparsing (>=3.1.1,<4.0.0)
